ifirma/__init__.py
ifirma/api.py
ifirma/config.py
ifirma/invoice.py
ifirma/request.py
ifirma/serializer.py
ifirma/yaml_parser.py
pnowosie.ifirma_api-1.3.0.dist-info/LICENSE
pnowosie.ifirma_api-1.3.0.dist-info/METADATA
pnowosie.ifirma_api-1.3.0.dist-info/WHEEL
pnowosie.ifirma_api-1.3.0.dist-info/top_level.txt
pnowosie.ifirma_api-1.3.0.dist-info/RECORD
