Metadata-Version: 2.1
Name: pnowosie.ifirma-api
Version: 1.3.0
Summary: IFirma API client
Home-page: https://github.com/pnowosie/ifirma-api
Author: Paweł Nowosielski
Author-email: nowosielski@gmail.com
License: UNKNOWN
Platform: UNKNOWN
Classifier: Programming Language :: Python :: 3
Classifier: License :: OSI Approved :: MIT License
Classifier: Operating System :: OS Independent
Requires-Python: >=3.8
Requires-Dist: requests
Requires-Dist: pyyaml
